openems/__init__.py
openems/__main__.py
openems/api.py
openems/exceptions.py
openems/utils/bridge.py
pyopenems-1.8.0.dist-info/licenses/LICENSE
tests/empty_test.py
pyopenems-1.8.0.dist-info/METADATA
pyopenems-1.8.0.dist-info/WHEEL
pyopenems-1.8.0.dist-info/top_level.txt
pyopenems-1.8.0.dist-info/RECORD
