Metadata-Version: 2.4
Name: pyopenems
Version: 1.8.0
Requires-Python: >=3.8
License-File: LICENSE
Requires-Dist: click<8.2,>=8.1
Requires-Dist: jsonrpc-websocket<3.2,>=3.1
Requires-Dist: pandas<2.4,>=2.0
Requires-Dist: asgiref<3.10,>=3.9
Dynamic: license-file
